netconan/__init__.py
netconan/anonymize_files.py
netconan/default_pwd_regexes.py
netconan/default_reserved_words.py
netconan/ip_anonymization.py
netconan/netconan.py
netconan/sensitive_item_removal.py
netconan_nsv-1.0a2.dist-info/LICENSE
netconan_nsv-1.0a2.dist-info/METADATA
netconan_nsv-1.0a2.dist-info/NOTICE
netconan_nsv-1.0a2.dist-info/WHEEL
netconan_nsv-1.0a2.dist-info/entry_points.txt
netconan_nsv-1.0a2.dist-info/top_level.txt
netconan_nsv-1.0a2.dist-info/RECORD
