Metadata-Version: 2.1
Name: netconan-nsv
Version: 1.0a2
Summary: Netconan network configuration anonymization utilities
Home-page: https://github.com/petercrocker/netconan
Author: Pete Crocker
Author-email: pete@petecrocker.com
License: Apache License 2.0
Keywords: network configuration anonymizer
Platform: UNKNOWN
Requires-Dist: bidict (<1.0.0)
Requires-Dist: configargparse (<1.0.0)
Requires-Dist: ipaddress (<2.0.0)
Requires-Dist: passlib (<2.0.0)
Requires-Dist: six (<2.0.0)
Requires-Dist: enum34 (<2.0.0) ; python_version < "3.4"
Provides-Extra: dev
Requires-Dist: flake8-docstrings (<2.0.0) ; extra == 'dev'
Requires-Dist: flake8 (<4.0.0) ; extra == 'dev'
Requires-Dist: pydocstyle (<4.0.0) ; extra == 'dev'
Provides-Extra: test
Requires-Dist: pytest-cov (<3.0.0) ; extra == 'test'
Requires-Dist: pytest (<5.0.0,>=4.6.0) ; extra == 'test'
Requires-Dist: requests-mock (<2.0.0) ; extra == 'test'
Requires-Dist: testfixtures (<7.0.0) ; extra == 'test'
Requires-Dist: zipp (<2.2) ; extra == 'test'
